ptero/__init__.py
ptero/application.py
ptero/client.py
ptero/control.py
ptero/models.py
ptero-0.2.2.dist-info/METADATA
ptero-0.2.2.dist-info/WHEEL
ptero-0.2.2.dist-info/top_level.txt
ptero-0.2.2.dist-info/RECORD
