Metadata-Version: 2.4
Name: ptero
Version: 0.2.2
Summary: An asynchronous, feature-rich Python wrapper for the Pterodactyl Panel API.
Author-email: Hotment <michatchuplay@gmail.com>
Project-URL: Homepage, https://github.com/Hotment/ptero-wrapper
Project-URL: Repository, https://github.com/Hotment/ptero-wrapper
Project-URL: Documentation, https://github.com/Hotment/Ptero-Wrapper/blob/main/DOCUMENTATION.md
Keywords: pterodactyl,api,wrapper,asyncio,panel
Classifier: Development Status :: 3 - Alpha
Classifier: Intended Audience :: Developers
Classifier: Programming Language :: Python :: 3
Classifier: Programming Language :: Python :: 3.8
Classifier: Programming Language :: Python :: 3.9
Classifier: Programming Language :: Python :: 3.10
Classifier: Programming Language :: Python :: 3.11
Classifier: Programming Language :: Python :: 3.12
Classifier: Programming Language :: Python :: 3.13
Classifier: Programming Language :: Python :: 3.14
Classifier: Topic :: Software Development :: Libraries :: Python Modules
Classifier: Operating System :: OS Independent
Classifier: Framework :: AsyncIO
Requires-Python: >=3.8
Requires-Dist: httpx>=0.20.0
Requires-Dist: websockets>=10.0
Requires-Dist: aiofiles>=22.1.0
